inteltwin/__about__.py
inteltwin/__init__.py
inteltwin-0.1.104.dist-info/METADATA
inteltwin-0.1.104.dist-info/WHEEL
inteltwin-0.1.104.dist-info/licenses/LICENSE
inteltwin-0.1.104.dist-info/licenses/LICENSE.txt
inteltwin-0.1.104.dist-info/RECORD
