Metadata-Version: 2.1
Name: inteltwin
Version: 0.1.104
Summary: The next generation digital twin
Project-URL: Documentation, https://github.com/unknown/inteltwin#readme
Project-URL: Issues, https://github.com/unknown/inteltwin/issues
Project-URL: Source, https://github.com/unknown/inteltwin
Author-email: Vincent Lee <vincent@akaun.com>
License-Expression: MIT
License-File: LICENSE
License-File: LICENSE.txt
Keywords: Digital Twin,Virtual Assistant
Classifier: Development Status :: 4 - Beta
Classifier: Programming Language :: Python
Classifier: Programming Language :: Python :: 3.7
Classifier: Programming Language :: Python :: 3.8
Classifier: Programming Language :: Python :: 3.9
Classifier: Programming Language :: Python :: 3.10
Classifier: Programming Language :: Python :: 3.11
Classifier: Programming Language :: Python :: Implementation :: CPython
Classifier: Programming Language :: Python :: Implementation :: PyPy
Requires-Python: >=3.7
